pratac/__init__.py
pratac/__main__.py
pratac/argparser.py
pratac/config.py
pratac/definitions.py
pratac/interactive.py
pratac-0.4.0.dist-info/LICENSE
pratac-0.4.0.dist-info/METADATA
pratac-0.4.0.dist-info/WHEEL
pratac-0.4.0.dist-info/entry_points.txt
pratac-0.4.0.dist-info/RECORD
