Metadata-Version: 2.3
Name: pratac
Version: 0.4.0
Summary: Python script designed to streamline dorm room cleaning assignments 
Author: Martin Lejko
Author-email: Martin.lejko@outlook.com
Requires-Python: >=3.11,<4.0
Classifier: Programming Language :: Python :: 3
Classifier: Programming Language :: Python :: 3.11
Classifier: Programming Language :: Python :: 3.12
Classifier: Programming Language :: Python :: 3.13
